setup.cfg
setup.py
start.py
start.egg-info/PKG-INFO
start.egg-info/SOURCES.txt
start.egg-info/dependency_links.txt
start.egg-info/entry_points.txt
start.egg-info/top_level.txt