Metadata-Version: 1.0
Name: start
Version: 0.2
Summary: Very simple command to start a single process from a Procfile
Home-page: https://github.com/aldryncore/start
Author: Divio AG
Author-email: aldryn@divio.ch
License: BSD
Platform: OS Independent
